age_verification_psehack/__init__.py
age_verification_psehack/apps.py
age_verification_psehack/middleware.py
age_verification_psehack/models.py
age_verification_psehack/settings.py
age_verification_psehack/tests.py
age_verification_psehack/urls.py
age_verification_psehack/views.py
age_verification_psehack/migrations/0001_initial.py
age_verification_psehack/migrations/__init__.py
age_verification_psehack-0.2.2.dist-info/METADATA
age_verification_psehack-0.2.2.dist-info/WHEEL
age_verification_psehack-0.2.2.dist-info/top_level.txt
age_verification_psehack-0.2.2.dist-info/RECORD
